MANIFEST.in
README.md
setup.cfg
setup.py
docs/authors.rst
docs/changelog.rst
docs/conf.py
docs/contributing.rst
docs/django_sphinx.py
docs/index.rst
docs/installation.rst
docs/license.rst
docs/readme.rst
docs/source.rst
waves/__init__.py
waves/adaptors/__init__.py
waves/adaptors/galaxy/__init__.py
waves/adaptors/galaxy/apps.py
waves/adaptors/galaxy/exception.py
waves/adaptors/galaxy/importers.py
waves/adaptors/galaxy/tests.py
waves/adaptors/galaxy/tool.py
waves/adaptors/galaxy/utils.py
waves/adaptors/galaxy/workflow.py
waves_galaxy_adaptors.egg-info/PKG-INFO
waves_galaxy_adaptors.egg-info/SOURCES.txt
waves_galaxy_adaptors.egg-info/dependency_links.txt
waves_galaxy_adaptors.egg-info/requires.txt
waves_galaxy_adaptors.egg-info/top_level.txt