Metadata-Version: 1.1
Name: waves-galaxy-adaptors
Version: 1.1.4.1
Summary: WAVES adaptor to interact with Galaxy remote platform
Home-page: https://github.com/lirmm/waves-galaxy
Author: LIRMM - MAB Laboratory - France
Author-email: vincent.lefort@lirmm.fr
License: GPLv3
Platform: UNKNOWN
Classifier: Environment :: Web Environment
Classifier: Framework :: Django
Classifier: Development Status :: 3 - Alpha
Classifier: Intended Audience :: Developers
Classifier: License :: OSI Approved :: GNU General Public License v3 (GPLv3)
Classifier: Programming Language :: Python :: 2.7
Classifier: Topic :: Utilities
Classifier: Topic :: System :: Distributed Computing
Classifier: Topic :: Internet :: WWW/HTTP :: WSGI :: Application
Classifier: Topic :: Scientific/Engineering :: Bio-Informatics
Classifier: Operating System :: Unix
